{
  "description": "Unicode homoglyph mappings for detecting lookalike characters",
  "cyrillicToLatin": {
    "а": { "latin": "a", "unicode": "U+0430", "name": "Cyrillic Small Letter A" },
    "с": { "latin": "c", "unicode": "U+0441", "name": "Cyrillic Small Letter Es" },
    "е": { "latin": "e", "unicode": "U+0435", "name": "Cyrillic Small Letter Ie" },
    "һ": { "latin": "h", "unicode": "U+04BB", "name": "Cyrillic Small Letter Shha" },
    "і": { "latin": "i", "unicode": "U+0456", "name": "Cyrillic Small Letter Byelorussian-Ukrainian I" },
    "ј": { "latin": "j", "unicode": "U+0458", "name": "Cyrillic Small Letter Je" },
    "о": { "latin": "o", "unicode": "U+043E", "name": "Cyrillic Small Letter O" },
    "р": { "latin": "p", "unicode": "U+0440", "name": "Cyrillic Small Letter Er" },
    "ѕ": { "latin": "s", "unicode": "U+0455", "name": "Cyrillic Small Letter Dze" },
    "ѵ": { "latin": "v", "unicode": "U+0475", "name": "Cyrillic Small Letter Izhitsa" },
    "х": { "latin": "x", "unicode": "U+0445", "name": "Cyrillic Small Letter Ha" },
    "у": { "latin": "y", "unicode": "U+0443", "name": "Cyrillic Small Letter U" },
    "А": { "latin": "A", "unicode": "U+0410", "name": "Cyrillic Capital Letter A" },
    "В": { "latin": "B", "unicode": "U+0412", "name": "Cyrillic Capital Letter Ve" },
    "С": { "latin": "C", "unicode": "U+0421", "name": "Cyrillic Capital Letter Es" },
    "Е": { "latin": "E", "unicode": "U+0415", "name": "Cyrillic Capital Letter Ie" },
    "Н": { "latin": "H", "unicode": "U+041D", "name": "Cyrillic Capital Letter En" },
    "І": { "latin": "I", "unicode": "U+0406", "name": "Cyrillic Capital Letter Byelorussian-Ukrainian I" },
    "К": { "latin": "K", "unicode": "U+041A", "name": "Cyrillic Capital Letter Ka" },
    "М": { "latin": "M", "unicode": "U+041C", "name": "Cyrillic Capital Letter Em" },
    "О": { "latin": "O", "unicode": "U+041E", "name": "Cyrillic Capital Letter O" },
    "Р": { "latin": "P", "unicode": "U+0420", "name": "Cyrillic Capital Letter Er" },
    "Т": { "latin": "T", "unicode": "U+0422", "name": "Cyrillic Capital Letter Te" },
    "Х": { "latin": "X", "unicode": "U+0425", "name": "Cyrillic Capital Letter Ha" }
  },
  "greekToLatin": {
    "α": { "latin": "a", "unicode": "U+03B1", "name": "Greek Small Letter Alpha" },
    "β": { "latin": "b", "unicode": "U+03B2", "name": "Greek Small Letter Beta" },
    "ε": { "latin": "e", "unicode": "U+03B5", "name": "Greek Small Letter Epsilon" },
    "η": { "latin": "n", "unicode": "U+03B7", "name": "Greek Small Letter Eta" },
    "ι": { "latin": "i", "unicode": "U+03B9", "name": "Greek Small Letter Iota" },
    "κ": { "latin": "k", "unicode": "U+03BA", "name": "Greek Small Letter Kappa" },
    "ν": { "latin": "v", "unicode": "U+03BD", "name": "Greek Small Letter Nu" },
    "ο": { "latin": "o", "unicode": "U+03BF", "name": "Greek Small Letter Omicron" },
    "ρ": { "latin": "p", "unicode": "U+03C1", "name": "Greek Small Letter Rho" },
    "τ": { "latin": "t", "unicode": "U+03C4", "name": "Greek Small Letter Tau" },
    "υ": { "latin": "u", "unicode": "U+03C5", "name": "Greek Small Letter Upsilon" },
    "χ": { "latin": "x", "unicode": "U+03C7", "name": "Greek Small Letter Chi" },
    "ω": { "latin": "w", "unicode": "U+03C9", "name": "Greek Small Letter Omega" },
    "Α": { "latin": "A", "unicode": "U+0391", "name": "Greek Capital Letter Alpha" },
    "Β": { "latin": "B", "unicode": "U+0392", "name": "Greek Capital Letter Beta" },
    "Ε": { "latin": "E", "unicode": "U+0395", "name": "Greek Capital Letter Epsilon" },
    "Η": { "latin": "H", "unicode": "U+0397", "name": "Greek Capital Letter Eta" },
    "Ι": { "latin": "I", "unicode": "U+0399", "name": "Greek Capital Letter Iota" },
    "Κ": { "latin": "K", "unicode": "U+039A", "name": "Greek Capital Letter Kappa" },
    "Μ": { "latin": "M", "unicode": "U+039C", "name": "Greek Capital Letter Mu" },
    "Ν": { "latin": "N", "unicode": "U+039D", "name": "Greek Capital Letter Nu" },
    "Ο": { "latin": "O", "unicode": "U+039F", "name": "Greek Capital Letter Omicron" },
    "Ρ": { "latin": "P", "unicode": "U+03A1", "name": "Greek Capital Letter Rho" },
    "Τ": { "latin": "T", "unicode": "U+03A4", "name": "Greek Capital Letter Tau" },
    "Χ": { "latin": "X", "unicode": "U+03A7", "name": "Greek Capital Letter Chi" },
    "Υ": { "latin": "Y", "unicode": "U+03A5", "name": "Greek Capital Letter Upsilon" }
  },
  "numberLetterSubstitutions": {
    "0": { "lookalike": "O", "reverse": true },
    "1": { "lookalike": "l", "reverse": true },
    "3": { "lookalike": "E", "reverse": false },
    "4": { "lookalike": "A", "reverse": false },
    "5": { "lookalike": "S", "reverse": true },
    "6": { "lookalike": "G", "reverse": false },
    "7": { "lookalike": "T", "reverse": false },
    "8": { "lookalike": "B", "reverse": true }
  },
  "specialCharacters": {
    "|": { "lookalike": "l", "unicode": "U+007C" },
    "!": { "lookalike": "i", "unicode": "U+0021" },
    "ı": { "lookalike": "i", "unicode": "U+0131", "name": "Latin Small Letter Dotless I" },
    "ℓ": { "lookalike": "l", "unicode": "U+2113", "name": "Script Small L" },
    "℮": { "lookalike": "e", "unicode": "U+212E", "name": "Estimated Symbol" },
    "∪": { "lookalike": "u", "unicode": "U+222A", "name": "Union" },
    "ⅰ": { "lookalike": "i", "unicode": "U+2170", "name": "Small Roman Numeral One" },
    "ⅱ": { "lookalike": "ii", "unicode": "U+2171", "name": "Small Roman Numeral Two" }
  }
}
